AnnoKit-1.0.0.data/scripts/AnnoGtf
annokit/__init__.py
annokit/gtf.py
AnnoKit-1.0.0.dist-info/LICENSE
AnnoKit-1.0.0.dist-info/METADATA
AnnoKit-1.0.0.dist-info/WHEEL
AnnoKit-1.0.0.dist-info/top_level.txt
AnnoKit-1.0.0.dist-info/RECORD
