Metadata-Version: 2.1
Name: AnnoKit
Version: 1.0.0
Summary: annotation toolkit.
Home-page: https://github.com/iOLIGO/AnnoKit
Author: cong wang
Author-email: 2119452560@qq.com
License: MIT
Keywords: bioinformatics,annotation file,gtf,gff
Classifier: Development Status :: 3 - Alpha
Classifier: Operating System :: POSIX
Classifier: Programming Language :: Python
Classifier: Programming Language :: Python :: 3
Classifier: Programming Language :: Python :: 3.7
Classifier: Programming Language :: Python :: 3.8
Classifier: Programming Language :: Python :: 3.9
Classifier: License :: OSI Approved :: MIT License
Classifier: Intended Audience :: Science/Research
Classifier: Topic :: Scientific/Engineering :: Bio-Informatics
Classifier: Topic :: Scientific/Engineering :: Information Analysis
Requires-Python: >=3.7, <4
License-File: LICENSE
Requires-Dist: intervaltree
Requires-Dist: pandas
Requires-Dist: loguru
